alumathvanguard/__init__.py
alumathvanguard/matrix_ops.py
tests/__init__.py
tests/test_matrix_ops.py
alumathvanguard-1.0.0.dist-info/METADATA
alumathvanguard-1.0.0.dist-info/WHEEL
alumathvanguard-1.0.0.dist-info/top_level.txt
alumathvanguard-1.0.0.dist-info/RECORD
