Metadata-Version: 2.4
Name: alumathvanguard
Version: 1.0.0
Summary: A fun matrix multiplication library with personality from Group 15
Home-page: https://github.com/izabayo7/Formative2Group15/tree/main/Group15MatrixMultiplier
Author: ALU Math Vanguard Group 15
Project-URL: Bug Reports, https://github.com/izabayo7/Formative2Group15/issues
Project-URL: Source, https://github.com/izabayo7/Formative2Group15/tree/main/Group15MatrixMultiplier
Keywords: matrix multiplication linear algebra education ALU
Classifier: Development Status :: 4 - Beta
Classifier: Intended Audience :: Education
Classifier: Intended Audience :: Developers
Classifier: Topic :: Scientific/Engineering :: Mathematics
Classifier: License :: OSI Approved :: MIT License
Requires-Python: >=3.7
Provides-Extra: dev
Requires-Dist: pytest>=6.0; extra == "dev"
Requires-Dist: pytest-cov; extra == "dev"
Requires-Dist: black; extra == "dev"
Requires-Dist: flake8; extra == "dev"
Dynamic: author
Dynamic: classifier
Dynamic: description
Dynamic: description-content-type
Dynamic: home-page
Dynamic: keywords
Dynamic: project-url
Dynamic: provides-extra
Dynamic: requires-python
Dynamic: summary
